[{"agency_service_statuses": [{"agency_id": 132, "vehicle_arrivals_pct": 0.6333333333, "scheduled_arrivals_pct": 0.3333333333}], "arrivals": [{"agency_id": 132, "vehicle_id": 4007520, "call_name": "2016", "stop_id": 4284294, "route_id": 4014238, "trip_id": 22814686, "timestamp": 1730496001, "type": "vehicle-based", "distance": 930.134, "headsign": null}, {"agency_id": 132, "vehicle_id": 4007500, "call_name": "2126", "stop_id": 4284294, "route_id": 4014238, "trip_id": 22814654, "timestamp": 1730496096, "type": "vehicle-based", "distance": 1348.69, "headsign": null}, {"agency_id": 132, "vehicle_id": 4007508, "call_name": "2128", "stop_id": 4284294, "route_id": 4014238, "trip_id": 22814654, "timestamp": 1730496464, "type": "vehicle-based", "distance": 2597.31, "headsign": null}, {"agency_id": 132, "vehicle_id": 4007516, "call_name": "2018", "stop_id": 4284294, "route_id": 4014238, "trip_id": 22814694, "timestamp": 1730497375, "type": "vehicle-based", "distance": 5452.68, "headsign": null}, {"agency_id": 132, "vehicle_id": 4007512, "call_name": "2017", "stop_id": 4284294, "route_id": 4014238, "trip_id": 22814680, "timestamp": 1730498913, "type": "vehicle-based", "distance": 8712.77, "headsign": null}, {"agency_id": 132, "vehicle_id": 4007520, "call_name": "2016", "stop_id": 4284296, "route_id": 4014238, "trip_id": 22814688, "timestamp": 1730496434, "type": "vehicle-based", "distance": 1554.54, "headsign": null}, {"agency_id": 132, "vehicle_id": 4007500, "call_name": "2126", "stop_id": 4284296, "route_id": 4014238, "trip_id": 22814656, "timestamp": 1730496520, "type": "vehicle-based", "distance": 1973.1, "headsign": null}, {"agency_id": 132, "vehicle_id": 4007508, "call_name": "2128", "stop_id": 4284296, "route_id": 4014238, "trip_id": 22814656, "timestamp": 1730496891, "type": "vehicle-based", "distance": 3221.72, "headsign": null}, {"agency_id": 132, "vehicle_id": 4007516, "call_name": "2018", "stop_id": 4284296, "route_id": 4014238, "trip_id": 22814696, "timestamp": 1730497801, "type": "vehicle-based", "distance": 6077.08, "headsign": null}, {"agency_id": 132, "vehicle_id": 4007500, "call_name": "2126", "stop_id": 4284298, "route_id": 4014238, "trip_id": 22814654, "timestamp": 1730495810, "type": "vehicle-based", "distance": 180.406, "headsign": null}, {"agency_id": 132, "vehicle_id": 4007508, "call_name": "2128", "stop_id": 4284298, "route_id": 4014238, "trip_id": 22814654, "timestamp": 1730496145, "type": "vehicle-based", "distance": 1429.03, "headsign": null}, {"agency_id": 132, "vehicle_id": 4007520, "call_name": "2016", "stop_id": 4284298, "route_id": 4014238, "trip_id": 22814688, "timestamp": 1730496559, "type": "vehicle-based", "distance": 2185.03, "headsign": null}, {"agency_id": 132, "vehicle_id": 4007500, "call_name": "2126", "stop_id": 4284298, "route_id": 4014238, "trip_id": 22814656, "timestamp": 1730496643, "type": "vehicle-based", "distance": 2603.59, "headsign": null}, {"agency_id": 132, "vehicle_id": 4007508, "call_name": "2128", "stop_id": 4284298, "route_id": 4014238, "trip_id": 22814656, "timestamp": 1730497015, "type": "vehicle-based", "distance": 3852.21, "headsign": null}, {"agency_id": 132, "vehicle_id": 4007516, "call_name": "2018", "stop_id": 4284298, "route_id": 4014238, "trip_id": 22814694, "timestamp": 1730497057, "type": "vehicle-based", "distance": 4284.39, "headsign": null}, {"agency_id": 132, "vehicle_id": 4007516, "call_name": "2018", "stop_id": 4284298, "route_id": 4014238, "trip_id": 22814696, "timestamp": 1730497925, "type": "vehicle-based", "distance": 6707.58, "headsign": null}, {"agency_id": 132, "vehicle_id": 4007512, "call_name": "2017", "stop_id": 4284298, "route_id": 4014238, "trip_id": 22814680, "timestamp": 1730498592, "type": "vehicle-based", "distance": 7544.49, "headsign": null}, {"agency_id": 132, "vehicle_id": 4007508, "call_name": "2128", "stop_id": 4284300, "route_id": 4014238, "trip_id": 22814654, "timestamp": 1730495986, "type": "vehicle-based", "distance": 962.83, "headsign": null}, {"agency_id": 132, "vehicle_id": 4007520, "call_name": "2016", "stop_id": 4284300, "route_id": 4014238, "trip_id": 22814688, "timestamp": 1730496679, "type": "vehicle-based", "distance": 2696.47, "headsign": null}, {"agency_id": 132, "vehicle_id": 4007500, "call_name": "2126", "stop_id": 4284300, "route_id": 4014238, "trip_id": 22814656, "timestamp": 1730496762, "type": "vehicle-based", "distance": 3115.03, "headsign": null}, {"agency_id": 132, "vehicle_id": 4007516, "call_name": "2018", "stop_id": 4284300, "route_id": 4014238, "trip_id": 22814694, "timestamp": 1730496899, "type": "vehicle-based", "distance": 3818.19, "headsign": null}, {"agency_id": 132, "vehicle_id": 4007508, "call_name": "2128", "stop_id": 4284300, "route_id": 4014238, "trip_id": 22814656, "timestamp": 1730497134, "type": "vehicle-based", "distance": 4363.65, "headsign": null}, {"agency_id": 132, "vehicle_id": 4007516, "call_name": "2018", "stop_id": 4284300, "route_id": 4014238, "trip_id": 22814696, "timestamp": 1730498044, "type": "vehicle-based", "distance": 7219.01, "headsign": null}, {"agency_id": 132, "vehicle_id": 4007512, "call_name": "2017", "stop_id": 4284300, "route_id": 4014238, "trip_id": 22814680, "timestamp": 1730498436, "type": "vehicle-based", "distance": 7078.29, "headsign": null}, {"agency_id": 132, "vehicle_id": 4007512, "call_name": "2017", "stop_id": 4284302, "route_id": 4014238, "trip_id": 22814680, "timestamp": 1730495802, "type": "vehicle-based", "distance": 239.066, "headsign": null}, {"agency_id": 132, "vehicle_id": 4007520, "call_name": "2016", "stop_id": 4284302, "route_id": 4014238, "trip_id": 22814688, "timestamp": 1730496815, "type": "vehicle-based", "distance": 3087.63, "headsign": null}, {"agency_id": 132, "vehicle_id": 4007500, "call_name": "2126", "stop_id": 4284302, "route_id": 4014238, "trip_id": 22814656, "timestamp": 1730496895, "type": "vehicle-based", "distance": 3506.19, "headsign": null}, {"agency_id": 132, "vehicle_id": 4007508, "call_name": "2128", "stop_id": 4284302, "route_id": 4014238, "trip_id": 22814656, "timestamp": 1730497270, "type": "vehicle-based", "distance": 4754.81, "headsign": null}, {"agency_id": 132, "vehicle_id": 4007516, "call_name": "2018", "stop_id": 4284302, "route_id": 4014238, "trip_id": 22814696, "timestamp": 1730498178, "type": "vehicle-based", "distance": 7610.17, "headsign": null}, {"agency_id": 132, "vehicle_id": 4007512, "call_name": "2017", "stop_id": 4284304, "route_id": 4014238, "trip_id": 22814680, "timestamp": 1730496033, "type": "vehicle-based", "distance": 920.791, "headsign": null}, {"agency_id": 132, "vehicle_id": 4007516, "call_name": "2018", "stop_id": 4284304, "route_id": 4014238, "trip_id": 22814694, "timestamp": 1730496465, "type": "vehicle-based", "distance": 2513.42, "headsign": null}, {"agency_id": 132, "vehicle_id": 4007520, "call_name": "2016", "stop_id": 4284304, "route_id": 4014238, "trip_id": 22814688, "timestamp": 1730497050, "type": "vehicle-based", "distance": 3769.35, "headsign": null}, {"agency_id": 132, "vehicle_id": 4007500, "call_name": "2126", "stop_id": 4284304, "route_id": 4014238, "trip_id": 22814656, "timestamp": 1730497128, "type": "vehicle-based", "distance": 4187.92, "headsign": null}, {"agency_id": 132, "vehicle_id": 4007508, "call_name": "2128", "stop_id": 4284304, "route_id": 4014238, "trip_id": 22814656, "timestamp": 1730497503, "type": "vehicle-based", "distance": 5436.54, "headsign": null}, {"agency_id": 132, "vehicle_id": 4007512, "call_name": "2017", "stop_id": 4284304, "route_id": 4014238, "trip_id": 22814680, "timestamp": 1730497995, "type": "vehicle-based", "distance": 5773.51, "headsign": null}, {"agency_id": 132, "vehicle_id": 4007516, "call_name": "2018", "stop_id": 4284304, "route_id": 4014238, "trip_id": 22814696, "timestamp": 1730498411, "type": "vehicle-based", "distance": 8291.9, "headsign": null}, {"agency_id": 132, "vehicle_id": 4007520, "call_name": "2016", "stop_id": 4284304, "route_id": 4014238, "trip_id": 22814688, "timestamp": 1730499010, "type": "vehicle-based", "distance": 8622.08, "headsign": null}, {"agency_id": 132, "vehicle_id": 4007500, "call_name": "2126", "stop_id": 4284304, "route_id": 4014238, "trip_id": 22814656, "timestamp": 1730499084, "type": "vehicle-based", "distance": 9040.64, "headsign": null}, {"agency_id": 132, "vehicle_id": 4007516, "call_name": "2018", "stop_id": 4284306, "route_id": 4014238, "trip_id": 22814694, "timestamp": 1730496189, "type": "vehicle-based", "distance": 1676.56, "headsign": null}, {"agency_id": 132, "vehicle_id": 4007512, "call_name": "2017", "stop_id": 4284306, "route_id": 4014238, "trip_id": 22814680, "timestamp": 1730496351, "type": "vehicle-based", "distance": 1754.5, "headsign": null}, {"agency_id": 132, "vehicle_id": 4007520, "call_name": "2016", "stop_id": 4284306, "route_id": 4014238, "trip_id": 22814688, "timestamp": 1730497368, "type": "vehicle-based", "distance": 4603.06, "headsign": null}, {"agency_id": 132, "vehicle_id": 4007500, "call_name": "2126", "stop_id": 4284306, "route_id": 4014238, "trip_id": 22814656, "timestamp": 1730497444, "type": "vehicle-based", "distance": 5021.62, "headsign": null}, {"agency_id": 132, "vehicle_id": 4007512, "call_name": "2017", "stop_id": 4284306, "route_id": 4014238, "trip_id": 22814680, "timestamp": 1730497712, "type": "vehicle-based", "distance": 4936.66, "headsign": null}, {"agency_id": 132, "vehicle_id": 4007508, "call_name": "2128", "stop_id": 4284306, "route_id": 4014238, "trip_id": 22814656, "timestamp": 1730497820, "type": "vehicle-based", "distance": 6270.24, "headsign": null}, {"agency_id": 132, "vehicle_id": 4007520, "call_name": "2016", "stop_id": 4284306, "route_id": 4014238, "trip_id": 22814688, "timestamp": 1730498727, "type": "vehicle-based", "distance": 7785.22, "headsign": null}, {"agency_id": 132, "vehicle_id": 4007516, "call_name": "2018", "stop_id": 4284306, "route_id": 4014238, "trip_id": 22814696, "timestamp": 1730498728, "type": "vehicle-based", "distance": 9125.6, "headsign": null}, {"agency_id": 132, "vehicle_id": 4007500, "call_name": "2126", "stop_id": 4284306, "route_id": 4014238, "trip_id": 22814656, "timestamp": 1730498801, "type": "vehicle-based", "distance": 8203.78, "headsign": null}, {"agency_id": 132, "vehicle_id": 4007508, "call_name": "2128", "stop_id": 4284306, "route_id": 4014238, "trip_id": 22814656, "timestamp": 1730499178, "type": "vehicle-based", "distance": 9452.4, "headsign": null}, {"agency_id": 132, "vehicle_id": 4007512, "call_name": "2017", "stop_id": 4284308, "route_id": 4014238, "trip_id": 22814680, "timestamp": 1730496853, "type": "vehicle-based", "distance": 3260.1, "headsign": null}, {"agency_id": 132, "vehicle_id": 4007520, "call_name": "2016", "stop_id": 4284308, "route_id": 4014238, "trip_id": 22814688, "timestamp": 1730497869, "type": "vehicle-based", "distance": 6108.66, "headsign": null}, {"agency_id": 132, "vehicle_id": 4007500, "call_name": "2126", "stop_id": 4284308, "route_id": 4014238, "trip_id": 22814656, "timestamp": 1730497944, "type": "vehicle-based", "distance": 6527.22, "headsign": null}, {"agency_id": 132, "vehicle_id": 4007508, "call_name": "2128", "stop_id": 4284308, "route_id": 4014238, "trip_id": 22814656, "timestamp": 1730498321, "type": "vehicle-based", "distance": 7775.84, "headsign": null}, {"agency_id": 132, "vehicle_id": 4007516, "call_name": "2018", "stop_id": 4284308, "route_id": 4014238, "trip_id": 22814696, "timestamp": 1730499228, "type": "vehicle-based", "distance": 10631.2, "headsign": null}, {"agency_id": 132, "vehicle_id": 4007508, "call_name": "2128", "stop_id": 4284310, "route_id": 4014238, "trip_id": 22814654, "timestamp": 1730495796, "type": "vehicle-based", "distance": 80.721, "headsign": null}, {"agency_id": 132, "vehicle_id": 4007516, "call_name": "2018", "stop_id": 4284310, "route_id": 4014238, "trip_id": 22814694, "timestamp": 1730496655, "type": "vehicle-based", "distance": 2936.08, "headsign": null}, {"agency_id": 132, "vehicle_id": 4007512, "call_name": "2017", "stop_id": 4284310, "route_id": 4014238, "trip_id": 22814680, "timestamp": 1730498188, "type": "vehicle-based", "distance": 6196.18, "headsign": null}, {"agency_id": 132, "vehicle_id": 4007520, "call_name": "2016", "stop_id": 4284310, "route_id": 4014238, "trip_id": 22814688, "timestamp": 1730499205, "type": "vehicle-based", "distance": 9044.75, "headsign": null}, {"agency_id": 132, "vehicle_id": 4007500, "call_name": "2126", "stop_id": 4284310, "route_id": 4014238, "trip_id": 22814656, "timestamp": 1730499279, "type": "vehicle-based", "distance": 9463.3, "headsign": null}, {"agency_id": 132, "vehicle_id": 4007508, "call_name": "2128", "stop_id": 4284312, "route_id": 4014238, "trip_id": 22814654, "timestamp": 1730495843, "type": "vehicle-based", "distance": 421.686, "headsign": null}, {"agency_id": 132, "vehicle_id": 4007516, "call_name": "2018", "stop_id": 4284312, "route_id": 4014238, "trip_id": 22814694, "timestamp": 1730496756, "type": "vehicle-based", "distance": 3277.05, "headsign": null}, {"agency_id": 132, "vehicle_id": 4007512, "call_name": "2017", "stop_id": 4284312, "route_id": 4014238, "trip_id": 22814680, "timestamp": 1730498290, "type": "vehicle-based", "distance": 6537.15, "headsign": null}, {"agency_id": 132, "vehicle_id": 4007520, "call_name": "2016", "stop_id": 4284312, "route_id": 4014238, "trip_id": 22814688, "timestamp": 1730499316, "type": "vehicle-based", "distance": 9385.71, "headsign": null}, {"agency_id": 132, "vehicle_id": 4007520, "call_name": "2016", "stop_id": 4284314, "route_id": 4014238, "trip_id": 22814686, "timestamp": 1730495859, "type": "vehicle-based", "distance": 562.893, "headsign": null}, {"agency_id": 132, "vehicle_id": 4007500, "call_name": "2126", "stop_id": 4284314, "route_id": 4014238, "trip_id": 22814654, "timestamp": 1730495960, "type": "vehicle-based", "distance": 981.453, "headsign": null}, {"agency_id": 132, "vehicle_id": 4007508, "call_name": "2128", "stop_id": 4284314, "route_id": 4014238, "trip_id": 22814654, "timestamp": 1730496325, "type": "vehicle-based", "distance": 2230.07, "headsign": null}, {"agency_id": 132, "vehicle_id": 4007516, "call_name": "2018", "stop_id": 4284314, "route_id": 4014238, "trip_id": 22814694, "timestamp": 1730497236, "type": "vehicle-based", "distance": 5085.44, "headsign": null}, {"agency_id": 132, "vehicle_id": 4007512, "call_name": "2017", "stop_id": 4284314, "route_id": 4014238, "trip_id": 22814680, "timestamp": 1730498774, "type": "vehicle-based", "distance": 8345.53, "headsign": null}, {"agency_id": 132, "vehicle_id": 4007492, "call_name": "2124", "stop_id": 4284294, "route_id": 4016220, "trip_id": 22815014, "timestamp": 1730495891, "type": "vehicle-based", "distance": 485.635, "headsign": null}, {"agency_id": 132, "vehicle_id": 4016259, "call_name": "2123", "stop_id": 4284294, "route_id": 4016220, "trip_id": 22814968, "timestamp": 1730497333, "type": "vehicle-based", "distance": 5204.44, "headsign": null}, {"agency_id": 132, "vehicle_id": 4016259, "call_name": "2123", "stop_id": 4284298, "route_id": 4016220, "trip_id": 22814968, "timestamp": 1730496974, "type": "vehicle-based", "distance": 4005.69, "headsign": null}, {"agency_id": 132, "vehicle_id": 4016259, "call_name": "2123", "stop_id": 4284300, "route_id": 4016220, "trip_id": 22814968, "timestamp": 1730496813, "type": "vehicle-based", "distance": 3539.47, "headsign": null}, {"agency_id": 132, "vehicle_id": 4007492, "call_name": "2124", "stop_id": 4284314, "route_id": 4016220, "trip_id": 22815014, "timestamp": 1730495785, "type": "vehicle-based", "distance": 88.389, "headsign": null}, {"agency_id": 132, "vehicle_id": 4016259, "call_name": "2123", "stop_id": 4284314, "route_id": 4016220, "trip_id": 22814968, "timestamp": 1730497178, "type": "vehicle-based", "distance": 4807.19, "headsign": null}, {"agency_id": 132, "vehicle_id": 4016259, "call_name": "2123", "stop_id": 4284316, "route_id": 4016220, "trip_id": 22814968, "timestamp": 1730495798, "type": "vehicle-based", "distance": 52.823, "headsign": null}, {"agency_id": 132, "vehicle_id": 4016259, "call_name": "2123", "stop_id": 4284316, "route_id": 4016220, "trip_id": 22814968, "timestamp": 1730496422, "type": "vehicle-based", "distance": 1983.71, "headsign": null}, {"agency_id": 132, "vehicle_id": 4016259, "call_name": "2123", "stop_id": 4284318, "route_id": 4016220, "trip_id": 22814968, "timestamp": 1730495911, "type": "vehicle-based", "distance": 454.861, "headsign": null}, {"agency_id": 132, "vehicle_id": 4016259, "call_name": "2123", "stop_id": 4284320, "route_id": 4016220, "trip_id": 22814968, "timestamp": 1730496119, "type": "vehicle-based", "distance": 713.416, "headsign": null}, {"agency_id": 132, "vehicle_id": 4020147, "call_name": "2953", "stop_id": 4284328, "route_id": 4017474, "trip_id": 22815400, "timestamp": 1730495797, "type": "vehicle-based", "distance": 52.707, "headsign": null}], "success": true, "vehicles": [{"id": 4007520, "num_cars": null, "service_status": "in_service", "agency_id": 132, "route_id": 4014238, "trip_id": 22814686, "TripStart": "0001-01-01T00:00:00Z", "TripEnd": "0001-01-01T00:00:00Z", "gtfs_trip_id": "", "direction": false, "stop_pattern_id": 839859, "call_name": "2016", "current_stop_id": null, "next_stop": 4284314, "arrival_status": "Late", "position": [42.3505, -71.10983], "heading": 251, "speed": 12, "segment_id": 4560819, "off_route": false, "timestamp": 1730495753000, "load": null, "apc_status": "up"}, {"id": 4007512, "num_cars": null, "service_status": "in_service", "agency_id": 132, "route_id": 4014238, "trip_id": 22814680, "TripStart": "0001-01-01T00:00:00Z", "TripEnd": "0001-01-01T00:00:00Z", "gtfs_trip_id": "", "direction": false, "stop_pattern_id": 839859, "call_name": "2017", "current_stop_id": null, "next_stop": 4284302, "arrival_status": "N/A", "position": [42.34888, -71.09797], "heading": 83, "speed": 11, "segment_id": 4560819, "off_route": false, "timestamp": 1730495754000, "load": 0.0625, "apc_status": "up"}, {"id": 4007508, "num_cars": null, "service_status": "in_service", "agency_id": 132, "route_id": 4014238, "trip_id": 22814654, "TripStart": "0001-01-01T00:00:00Z", "TripEnd": "0001-01-01T00:00:00Z", "gtfs_trip_id": "", "direction": false, "stop_pattern_id": 839859, "call_name": "2128", "current_stop_id": null, "next_stop": 4284310, "arrival_status": "Early", "position": [42.350792, -71.08966], "heading": 193, "speed": 11, "segment_id": 4560819, "off_route": false, "timestamp": 1730495753000, "load": null, "apc_status": "up"}, {"id": 4020147, "num_cars": null, "service_status": "in_service", "agency_id": 132, "route_id": 4017474, "trip_id": 22815400, "TripStart": "0001-01-01T00:00:00Z", "TripEnd": "0001-01-01T00:00:00Z", "gtfs_trip_id": "", "direction": false, "stop_pattern_id": 839869, "call_name": "2953", "current_stop_id": null, "next_stop": 4284328, "arrival_status": "Early", "position": [42.35427, -71.10479], "heading": 200, "speed": 0, "segment_id": 4560829, "off_route": false, "timestamp": 1730495750000, "load": null, "apc_status": "up"}, {"id": 4008320, "num_cars": null, "service_status": "in_service", "agency_id": 132, "route_id": 4016218, "trip_id": 22814824, "TripStart": "0001-01-01T00:00:00Z", "TripEnd": "0001-01-01T00:00:00Z", "gtfs_trip_id": "", "direction": false, "stop_pattern_id": 839861, "call_name": "2019", "current_stop_id": null, "next_stop": 0, "arrival_status": "N/A", "position": [42.35324, -71.11815], "heading": 306, "speed": 0, "segment_id": 4560821, "off_route": false, "timestamp": 1730495753000, "load": 0.0125, "apc_status": "up"}, {"id": 4020145, "num_cars": null, "service_status": "in_service", "agency_id": 132, "route_id": 4017474, "trip_id": 22815458, "TripStart": "0001-01-01T00:00:00Z", "TripEnd": "0001-01-01T00:00:00Z", "gtfs_trip_id": "", "direction": false, "stop_pattern_id": 839869, "call_name": "2952", "current_stop_id": 4284328, "next_stop": 0, "arrival_status": "N/A", "position": [42.3549, -71.10519], "heading": 318, "speed": 9.65604, "segment_id": 4560829, "off_route": false, "timestamp": 1730495752000, "load": null, "apc_status": "up"}, {"id": 4016259, "num_cars": null, "service_status": "in_service", "agency_id": 132, "route_id": 4016220, "trip_id": 22814968, "TripStart": "0001-01-01T00:00:00Z", "TripEnd": "0001-01-01T00:00:00Z", "gtfs_trip_id": "", "direction": false, "stop_pattern_id": 839863, "call_name": "2123", "current_stop_id": 4284316, "next_stop": 4284316, "arrival_status": "N/A", "position": [42.345165, -71.10441], "heading": 154, "speed": 0, "segment_id": 4560823, "off_route": false, "timestamp": 1730495752000, "load": 0, "apc_status": "up"}, {"id": 4007492, "num_cars": null, "service_status": "in_service", "agency_id": 132, "route_id": 4016220, "trip_id": 22815014, "TripStart": "0001-01-01T00:00:00Z", "TripEnd": "0001-01-01T00:00:00Z", "gtfs_trip_id": "", "direction": false, "stop_pattern_id": 839863, "call_name": "2124", "current_stop_id": 4284314, "next_stop": 4284314, "arrival_status": "Early", "position": [42.351257, -71.11614], "heading": 227, "speed": 0, "segment_id": 4560823, "off_route": false, "timestamp": 1730495753000, "load": 0.72, "apc_status": "up"}, {"id": 4007500, "num_cars": null, "service_status": "in_service", "agency_id": 132, "route_id": 4014238, "trip_id": 22814654, "TripStart": "0001-01-01T00:00:00Z", "TripEnd": "0001-01-01T00:00:00Z", "gtfs_trip_id": "", "direction": false, "stop_pattern_id": 839859, "call_name": "2126", "current_stop_id": null, "next_stop": 4284298, "arrival_status": "N/A", "position": [42.349815, -71.104065], "heading": 218, "speed": 0, "segment_id": 4560819, "off_route": false, "timestamp": 1730495751000, "load": null, "apc_status": "up"}, {"id": 4007516, "num_cars": null, "service_status": "in_service", "agency_id": 132, "route_id": 4014238, "trip_id": 22814694, "TripStart": "0001-01-01T00:00:00Z", "TripEnd": "0001-01-01T00:00:00Z", "gtfs_trip_id": "", "direction": false, "stop_pattern_id": 839859, "call_name": "2018", "current_stop_id": 4284308, "next_stop": 4284306, "arrival_status": "N/A", "position": [42.335396, -71.07085], "heading": 308, "speed": 0, "segment_id": 4560819, "off_route": false, "timestamp": 1730495753000, "load": 0.5125, "apc_status": "up"}], "_type": "dict"}]